scrapydweb/__init__.py
scrapydweb/__version__.py
scrapydweb/common.py
scrapydweb/default_settings.py
scrapydweb/models.py
scrapydweb/run.py
scrapydweb/scrapydweb_settings_v10.py
scrapydweb/vars.py
scrapydweb/data/demo_projects/ScrapydWeb_demo/scrapy.cfg
scrapydweb/data/demo_projects/ScrapydWeb_demo/ScrapydWeb_demo/__init__.py
scrapydweb/data/demo_projects/ScrapydWeb_demo/ScrapydWeb_demo/items.py
scrapydweb/data/demo_projects/ScrapydWeb_demo/ScrapydWeb_demo/middlewares.py
scrapydweb/data/demo_projects/ScrapydWeb_demo/ScrapydWeb_demo/pipelines.py
scrapydweb/data/demo_projects/ScrapydWeb_demo/ScrapydWeb_demo/settings.py
scrapydweb/data/demo_projects/ScrapydWeb_demo/ScrapydWeb_demo/spiders/__init__.py
scrapydweb/data/demo_projects/ScrapydWeb_demo/ScrapydWeb_demo/spiders/test.py
scrapydweb/data/parse/ScrapydWeb_demo.log
scrapydweb/static/css/dropdown.css
scrapydweb/static/css/dropdown_mobileui.css
scrapydweb/static/css/icon_upload_icon_right.css
scrapydweb/static/css/multinode.css
scrapydweb/static/css/stacktable.css
scrapydweb/static/css/stats.css
scrapydweb/static/css/style.css
scrapydweb/static/css/style_mobileui.css
scrapydweb/static/css/utf8.css
scrapydweb/static/css/utf8_mobileui.css
scrapydweb/static/element-ui@2.4.6/lib/index.js
scrapydweb/static/element-ui@2.4.6/lib/theme-chalk/index.css
scrapydweb/static/element-ui@2.4.6/lib/theme-chalk/fonts/element-icons.woff
scrapydweb/static/icon/fav.ico
scrapydweb/static/icon/fav.png
scrapydweb/static/icon/spider-man-spiderman-face-mask-round-avatar-512.png
scrapydweb/static/icon/spiderman.png
scrapydweb/static/js/common.js
scrapydweb/static/js/echarts.min.js
scrapydweb/static/js/github_buttons.html
scrapydweb/static/js/github_buttons.js
scrapydweb/static/js/htmx.min.js
scrapydweb/static/js/icons_menu.js
scrapydweb/static/js/jquery.min.js
scrapydweb/static/js/multinode.js
scrapydweb/static/js/stacktable.js
scrapydweb/static/js/stats.js
scrapydweb/static/js/vue.min.js
scrapydweb/templates/500.html
scrapydwebx-1.5.8.dist-info/LICENSE
scrapydwebx-1.5.8.dist-info/METADATA
scrapydwebx-1.5.8.dist-info/WHEEL
scrapydwebx-1.5.8.dist-info/entry_points.txt
scrapydwebx-1.5.8.dist-info/top_level.txt
scrapydwebx-1.5.8.dist-info/RECORD
