Metadata-Version: 2.1
Name: scrapydwebx
Version: 1.5.8
Summary: Web app for Scrapyd cluster management, with support for Scrapy log analysis & visualization.
Home-page: https://github.com/payala/scrapydwebx
Author: payala
Author-email: ppayala@gmail.com
License: GNU General Public License v3.0
Classifier: License :: OSI Approved :: GNU General Public License v3 (GPLv3)
Classifier: Programming Language :: Python :: 3.6
Classifier: Programming Language :: Python :: 3.7
Classifier: Programming Language :: Python :: 3.8
Classifier: Programming Language :: Python :: 3.9
Classifier: Programming Language :: Python :: 3.10
Classifier: Programming Language :: Python :: 3.11
Classifier: Programming Language :: Python :: 3.12
Requires-Python: >=3.6
License-File: LICENSE
Requires-Dist: APScheduler ==3.6.0
Requires-Dist: click ==7.1.2
Requires-Dist: colorama ==0.4.0
Requires-Dist: Flask ==2.0.0
Requires-Dist: Flask-Compress ==1.4.0
Requires-Dist: Flask-SQLAlchemy ==2.4.0
Requires-Dist: idna ==2.7
Requires-Dist: itsdangerous ==2.0.0
Requires-Dist: Jinja2 ==3.0.0
Requires-Dist: logparser ==0.8.2
Requires-Dist: MarkupSafe ==2.0.0
Requires-Dist: pexpect ==4.7.0
Requires-Dist: ptyprocess ==0.6.0
Requires-Dist: pytz ==2018.9
Requires-Dist: requests >=2.21.0
Requires-Dist: setuptools >=40.6.3
Requires-Dist: six ==1.16.0
Requires-Dist: SQLAlchemy ==1.3.24
Requires-Dist: tzlocal ==1.5.1
Requires-Dist: w3lib ==2.0.0
Requires-Dist: Werkzeug ==2.0.0
